tiktok_driver/__init__.py
tiktok_driver/_classes.py
tiktok_driver/_tiktok.py
tiktok_driver/providers/__init__.py
tiktok_driver/providers/tiksave.py
tiktok_driver-0.1.1.dist-info/METADATA
tiktok_driver-0.1.1.dist-info/WHEEL
tiktok_driver-0.1.1.dist-info/RECORD
