Metadata-Version: 2.1
Name: tiktok-driver
Version: 0.1.1
Summary: 
Author: lockermanwxlf
Requires-Python: >=3.9,<4.0
Classifier: Programming Language :: Python :: 3
Classifier: Programming Language :: Python :: 3.9
Classifier: Programming Language :: Python :: 3.10
Classifier: Programming Language :: Python :: 3.11
Classifier: Programming Language :: Python :: 3.12
Requires-Dist: beautifulsoup4 (>=4.12.3,<5.0.0)
Requires-Dist: fake-useragent (>=1.5.1,<2.0.0)
Requires-Dist: nodriver (>=0.34,<0.35)
Requires-Dist: requests (>=2.32.3,<3.0.0)
